gsrecon/__init__.py
gsrecon/converter.py
gsrecon/distortion.py
gsrecon/train.py
gaussian_reconstruction-1.6.dist-info/METADATA
gaussian_reconstruction-1.6.dist-info/WHEEL
gaussian_reconstruction-1.6.dist-info/top_level.txt
gaussian_reconstruction-1.6.dist-info/RECORD
