Metadata-Version: 2.1
Name: gaussian-reconstruction
Version: 1.6
Summary: UNKNOWN
Home-page: UNKNOWN
Author: BerryChen
License: UNKNOWN
Platform: UNKNOWN
Requires-Dist: requests
